[
  {
    "anonymous": false,
    "inputs": [
      {
        "indexed": false,
        "internalType": "enum CollectionContract.Category",
        "name": "",
        "type": "uint8"
      },
      {
        "indexed": false,
        "internalType": "string",
        "name": "collectionName",
        "type": "string"
      },
      {
        "indexed": false,
        "internalType": "string",
        "name": "information",
        "type": "string"
      },
      {
        "indexed": false,
        "internalType": "string",
        "name": "url",
        "type": "string"
      },
      {
        "indexed": false,
        "internalType": "address",
        "name": "collectionAddress",
        "type": "address"
      },
      {
        "indexed": false,
        "internalType": "address",
        "name": "owner",
        "type": "address"
      }
    ],
    "name": "createdCollection",
    "type": "event"
  },
  {
    "inputs": [],
    "name": "collection",
    "outputs": [
      {
        "internalType": "contract MyToken",
        "name": "",
        "type": "address"
      }
    ],
    "stateMutability": "view",
    "type": "function"
  },
  {
    "inputs": [
      {
        "internalType": "string",
        "name": "_collectionName",
        "type": "string"
      },
      {
        "internalType": "string",
        "name": "_url",
        "type": "string"
      },
      {
        "internalType": "string",
        "name": "_information",
        "type": "string"
      },
      {
        "internalType": "enum CollectionContract.Category",
        "name": "_category",
        "type": "uint8"
      }
    ],
    "name": "createCollection",
    "outputs": [],
    "stateMutability": "nonpayable",
    "type": "function"
  }
]